{
  "openapi": "3.0.3",
  "info": {
    "title": "RAG Chat API",
    "version": "1.0.0",
    "description": "Upload PDF documents, process them into vector embeddings, and chat with them using RAG (Retrieval-Augmented Generation).\n\n## Auth Flow\nRegister or login to get a JWT bearer token, then send it in the `Authorization` header for protected endpoints."
  },
  "servers": [
    {
      "url": "http://localhost:8000",
      "description": "Local development server"
    }
  ],
  "paths": {
    "/api/health": {
      "get": {
        "tags": ["health"],
        "summary": "Health check",
        "operationId": "healthCheck",
        "responses": {
          "200": {
            "description": "Service is healthy",
            "content": {
              "application/json": {
                "schema": {
                  "type": "object",
                  "properties": {
                    "status": { "type": "string", "example": "ok" }
                  }
                }
              }
            }
          }
        }
      }
    },
    "/api/auth/register": {
      "post": {
        "tags": ["auth"],
        "summary": "Register a new user",
        "operationId": "registerUser",
        "requestBody": {
          "required": true,
          "content": {
            "application/json": {
              "schema": {
                "$ref": "#/components/schemas/RegisterRequest"
              }
            }
          }
        },
        "responses": {
          "201": {
            "description": "User created",
            "content": {
              "application/json": {
                "schema": {
                  "$ref": "#/components/schemas/UserResponse"
                }
              }
            }
          },
          "409": {
            "description": "Email already registered",
            "content": {
              "application/json": {
                "schema": {
                  "$ref": "#/components/schemas/ErrorResponse"
                },
                "example": {
                  "detail": "Email already registered"
                }
              }
            }
          }
        }
      }
    },
    "/api/auth/login": {
      "post": {
        "tags": ["auth"],
        "summary": "Login and get JWT token",
        "operationId": "loginUser",
        "requestBody": {
          "required": true,
          "content": {
            "application/json": {
              "schema": {
                "$ref": "#/components/schemas/LoginRequest"
              }
            }
          }
        },
        "responses": {
          "200": {
            "description": "Successful login",
            "content": {
              "application/json": {
                "schema": {
                  "$ref": "#/components/schemas/TokenResponse"
                }
              }
            }
          },
          "401": {
            "description": "Invalid credentials",
            "content": {
              "application/json": {
                "schema": {
                  "$ref": "#/components/schemas/ErrorResponse"
                },
                "example": {
                  "detail": "Invalid email or password"
                }
              }
            }
          }
        }
      }
    },
    "/api/auth/me": {
      "get": {
        "tags": ["auth"],
        "summary": "Get current authenticated user",
        "operationId": "getCurrentUser",
        "security": [{ "bearerAuth": [] }],
        "responses": {
          "200": {
            "description": "Current user info",
            "content": {
              "application/json": {
                "schema": {
                  "$ref": "#/components/schemas/UserResponse"
                }
              }
            }
          },
          "401": {
            "description": "Missing or invalid token",
            "content": {
              "application/json": {
                "schema": {
                  "$ref": "#/components/schemas/ErrorResponse"
                }
              }
            }
          }
        }
      }
    },
    "/api/documents/upload": {
      "post": {
        "tags": ["documents"],
        "summary": "Upload a PDF document for processing",
        "operationId": "uploadDocument",
        "security": [{ "bearerAuth": [] }],
        "requestBody": {
          "required": true,
          "content": {
            "multipart/form-data": {
              "schema": {
                "type": "object",
                "required": ["file"],
                "properties": {
                  "file": {
                    "type": "string",
                    "format": "binary",
                    "description": "PDF file to upload"
                  }
                }
              }
            }
          }
        },
        "responses": {
          "201": {
            "description": "Document uploaded and processing enqueued",
            "content": {
              "application/json": {
                "schema": {
                  "$ref": "#/components/schemas/UploadResponse"
                }
              }
            }
          },
          "400": {
            "description": "Invalid file type (only PDF allowed)",
            "content": {
              "application/json": {
                "schema": {
                  "$ref": "#/components/schemas/ErrorResponse"
                }
              }
            }
          },
          "401": {
            "description": "Unauthorized",
            "content": {
              "application/json": {
                "schema": {
                  "$ref": "#/components/schemas/ErrorResponse"
                }
              }
            }
          }
        }
      }
    },
    "/api/documents": {
      "get": {
        "tags": ["documents"],
        "summary": "List user's documents",
        "operationId": "listDocuments",
        "security": [{ "bearerAuth": [] }],
        "responses": {
          "200": {
            "description": "List of documents",
            "content": {
              "application/json": {
                "schema": {
                  "$ref": "#/components/schemas/DocumentListResponse"
                }
              }
            }
          },
          "401": {
            "description": "Unauthorized",
            "content": {
              "application/json": {
                "schema": {
                  "$ref": "#/components/schemas/ErrorResponse"
                }
              }
            }
          }
        }
      }
    },
    "/api/documents/{document_id}": {
      "get": {
        "tags": ["documents"],
        "summary": "Get a single document by ID",
        "operationId": "getDocument",
        "security": [{ "bearerAuth": [] }],
        "parameters": [
          {
            "name": "document_id",
            "in": "path",
            "required": true,
            "schema": { "type": "string", "format": "uuid" }
          }
        ],
        "responses": {
          "200": {
            "description": "Document details",
            "content": {
              "application/json": {
                "schema": {
                  "$ref": "#/components/schemas/DocumentResponse"
                }
              }
            }
          },
          "401": {
            "description": "Unauthorized",
            "content": {
              "application/json": {
                "schema": {
                  "$ref": "#/components/schemas/ErrorResponse"
                }
              }
            }
          },
          "404": {
            "description": "Document not found",
            "content": {
              "application/json": {
                "schema": {
                  "$ref": "#/components/schemas/ErrorResponse"
                }
              }
            }
          }
        }
      },
      "delete": {
        "tags": ["documents"],
        "summary": "Soft-delete a document",
        "operationId": "deleteDocument",
        "security": [{ "bearerAuth": [] }],
        "parameters": [
          {
            "name": "document_id",
            "in": "path",
            "required": true,
            "schema": { "type": "string", "format": "uuid" }
          }
        ],
        "responses": {
          "204": {
            "description": "Document deleted (no content)"
          },
          "401": {
            "description": "Unauthorized",
            "content": {
              "application/json": {
                "schema": {
                  "$ref": "#/components/schemas/ErrorResponse"
                }
              }
            }
          },
          "404": {
            "description": "Document not found",
            "content": {
              "application/json": {
                "schema": {
                  "$ref": "#/components/schemas/ErrorResponse"
                }
              }
            }
          }
        }
      }
    },
    "/api/chat/sessions": {
      "post": {
        "tags": ["chat"],
        "summary": "Create a new chat session for a completed document",
        "operationId": "createChatSession",
        "security": [{ "bearerAuth": [] }],
        "requestBody": {
          "required": true,
          "content": {
            "application/json": {
              "schema": {
                "$ref": "#/components/schemas/CreateSessionRequest"
              }
            }
          }
        },
        "responses": {
          "201": {
            "description": "Chat session created",
            "content": {
              "application/json": {
                "schema": {
                  "$ref": "#/components/schemas/CreateSessionResponse"
                }
              }
            }
          },
          "400": {
            "description": "Document is not completed",
            "content": {
              "application/json": {
                "schema": {
                  "$ref": "#/components/schemas/ErrorResponse"
                },
                "example": {
                  "detail": "Document is pending, must be completed"
                }
              }
            }
          },
          "401": {
            "description": "Unauthorized",
            "content": {
              "application/json": {
                "schema": {
                  "$ref": "#/components/schemas/ErrorResponse"
                }
              }
            }
          },
          "404": {
            "description": "Document not found",
            "content": {
              "application/json": {
                "schema": {
                  "$ref": "#/components/schemas/ErrorResponse"
                }
              }
            }
          }
        }
      },
      "get": {
        "tags": ["chat"],
        "summary": "List user's chat sessions",
        "operationId": "listChatSessions",
        "security": [{ "bearerAuth": [] }],
        "responses": {
          "200": {
            "description": "List of chat sessions",
            "content": {
              "application/json": {
                "schema": {
                  "$ref": "#/components/schemas/SessionListResponse"
                }
              }
            }
          },
          "401": {
            "description": "Unauthorized",
            "content": {
              "application/json": {
                "schema": {
                  "$ref": "#/components/schemas/ErrorResponse"
                }
              }
            }
          }
        }
      }
    },
    "/api/chat/sessions/{session_id}/messages": {
      "post": {
        "tags": ["chat"],
        "summary": "Send a message in a chat session and get a RAG-powered reply",
        "operationId": "sendMessage",
        "security": [{ "bearerAuth": [] }],
        "parameters": [
          {
            "name": "session_id",
            "in": "path",
            "required": true,
            "schema": { "type": "string", "format": "uuid" }
          }
        ],
        "requestBody": {
          "required": true,
          "content": {
            "application/json": {
              "schema": {
                "$ref": "#/components/schemas/SendMessageRequest"
              }
            }
          }
        },
        "responses": {
          "200": {
            "description": "Assistant reply",
            "content": {
              "application/json": {
                "schema": {
                  "$ref": "#/components/schemas/MessageResponse"
                }
              }
            }
          },
          "401": {
            "description": "Unauthorized",
            "content": {
              "application/json": {
                "schema": {
                  "$ref": "#/components/schemas/ErrorResponse"
                }
              }
            }
          },
          "404": {
            "description": "Chat session not found",
            "content": {
              "application/json": {
                "schema": {
                  "$ref": "#/components/schemas/ErrorResponse"
                }
              }
            }
          }
        }
      },
      "get": {
        "tags": ["chat"],
        "summary": "Get message history for a chat session",
        "operationId": "getMessages",
        "security": [{ "bearerAuth": [] }],
        "parameters": [
          {
            "name": "session_id",
            "in": "path",
            "required": true,
            "schema": { "type": "string", "format": "uuid" }
          }
        ],
        "responses": {
          "200": {
            "description": "Message history",
            "content": {
              "application/json": {
                "schema": {
                  "$ref": "#/components/schemas/MessageListResponse"
                }
              }
            }
          },
          "401": {
            "description": "Unauthorized",
            "content": {
              "application/json": {
                "schema": {
                  "$ref": "#/components/schemas/ErrorResponse"
                }
              }
            }
          },
          "404": {
            "description": "Chat session not found",
            "content": {
              "application/json": {
                "schema": {
                  "$ref": "#/components/schemas/ErrorResponse"
                }
              }
            }
          }
        }
      }
    }
  },
  "components": {
    "securitySchemes": {
      "bearerAuth": {
        "type": "http",
        "scheme": "bearer",
        "bearerFormat": "JWT",
        "description": "JWT access token obtained from `/api/auth/login`"
      }
    },
    "schemas": {
      "ErrorResponse": {
        "type": "object",
        "required": ["detail"],
        "properties": {
          "detail": {
            "type": "string",
            "description": "Error message"
          }
        }
      },
      "RegisterRequest": {
        "type": "object",
        "required": ["email", "password"],
        "properties": {
          "email": {
            "type": "string",
            "format": "email",
            "example": "user@example.com"
          },
          "password": {
            "type": "string",
            "minLength": 1,
            "example": "securepassword123"
          }
        }
      },
      "LoginRequest": {
        "type": "object",
        "required": ["email", "password"],
        "properties": {
          "email": {
            "type": "string",
            "format": "email",
            "example": "user@example.com"
          },
          "password": {
            "type": "string",
            "minLength": 1,
            "example": "securepassword123"
          }
        }
      },
      "TokenResponse": {
        "type": "object",
        "required": ["access_token", "token_type"],
        "properties": {
          "access_token": {
            "type": "string",
            "description": "JWT access token",
            "example": "eyJhbGciOiJIUzI1NiIs..."
          },
          "token_type": {
            "type": "string",
            "example": "bearer"
          }
        }
      },
      "UserResponse": {
        "type": "object",
        "required": ["id", "email"],
        "properties": {
          "id": {
            "type": "string",
            "format": "uuid",
            "example": "d290f1ee-6c54-4b01-90e6-d701748f0851"
          },
          "email": {
            "type": "string",
            "format": "email",
            "example": "user@example.com"
          }
        }
      },
      "UploadResponse": {
        "type": "object",
        "required": ["id", "status"],
        "properties": {
          "id": {
            "type": "string",
            "format": "uuid",
            "description": "Document ID",
            "example": "d290f1ee-6c54-4b01-90e6-d701748f0851"
          },
          "status": {
            "$ref": "#/components/schemas/ProcessingStatus"
          }
        }
      },
      "ProcessingStatus": {
        "type": "string",
        "enum": ["pending", "processing", "completed", "failed"],
        "description": "Processing status of a document"
      },
      "DocumentResponse": {
        "type": "object",
        "required": ["id", "original_filename", "mime_type", "status", "created_at"],
        "properties": {
          "id": {
            "type": "string",
            "format": "uuid"
          },
          "title": {
            "type": "string",
            "nullable": true,
            "example": "Research Paper"
          },
          "original_filename": {
            "type": "string",
            "example": "paper.pdf"
          },
          "mime_type": {
            "type": "string",
            "example": "application/pdf"
          },
          "status": {
            "$ref": "#/components/schemas/ProcessingStatus"
          },
          "processing_error": {
            "type": "string",
            "nullable": true,
            "description": "Error message if processing failed"
          },
          "created_at": {
            "type": "string",
            "format": "date-time",
            "example": "2026-06-25T12:00:00Z"
          }
        }
      },
      "DocumentListResponse": {
        "type": "object",
        "required": ["documents"],
        "properties": {
          "documents": {
            "type": "array",
            "items": {
              "$ref": "#/components/schemas/DocumentResponse"
            }
          }
        }
      },
      "CreateSessionRequest": {
        "type": "object",
        "required": ["document_id"],
        "properties": {
          "document_id": {
            "type": "string",
            "format": "uuid",
            "description": "ID of the completed document to chat with",
            "example": "d290f1ee-6c54-4b01-90e6-d701748f0851"
          }
        }
      },
      "CreateSessionResponse": {
        "type": "object",
        "required": ["id", "document_id", "title"],
        "properties": {
          "id": {
            "type": "string",
            "format": "uuid",
            "description": "Chat session ID"
          },
          "document_id": {
            "type": "string",
            "format": "uuid"
          },
          "title": {
            "type": "string",
            "example": "New Chat"
          }
        }
      },
      "SessionResponse": {
        "type": "object",
        "required": ["id", "document_id", "title", "created_at"],
        "properties": {
          "id": {
            "type": "string",
            "format": "uuid"
          },
          "document_id": {
            "type": "string",
            "format": "uuid"
          },
          "title": {
            "type": "string",
            "example": "New Chat"
          },
          "created_at": {
            "type": "string",
            "format": "date-time"
          }
        }
      },
      "SessionListResponse": {
        "type": "object",
        "required": ["sessions"],
        "properties": {
          "sessions": {
            "type": "array",
            "items": {
              "$ref": "#/components/schemas/SessionResponse"
            }
          }
        }
      },
      "SendMessageRequest": {
        "type": "object",
        "required": ["content"],
        "properties": {
          "content": {
            "type": "string",
            "description": "User's message",
            "example": "What is the main conclusion of this paper?"
          }
        }
      },
      "MessageRole": {
        "type": "string",
        "enum": ["user", "assistant"],
        "description": "Who sent the message"
      },
      "MessageResponse": {
        "type": "object",
        "required": ["id", "role", "content", "created_at"],
        "properties": {
          "id": {
            "type": "string",
            "format": "uuid"
          },
          "role": {
            "$ref": "#/components/schemas/MessageRole"
          },
          "content": {
            "type": "string"
          },
          "created_at": {
            "type": "string",
            "format": "date-time"
          }
        }
      },
      "MessageListResponse": {
        "type": "object",
        "required": ["messages"],
        "properties": {
          "messages": {
            "type": "array",
            "items": {
              "$ref": "#/components/schemas/MessageResponse"
            }
          }
        }
      }
    }
  }
}
